Workbook

Sheet Start here
B2: Bank Reconciliation and AP/AR - ready to use
B3: Timothy Ting - chimsyt.github.io - formulas pre-filled, no data. Start at the Bank sheet.
B6: What it does
B8: Takes a bank statement and a ledger of invoices and bills, matches them against each other, and reports what does not reconcile - from both directions. It then ages the receivables and builds the week's supplier payment run from the same data, so nothing is typed twice.
B10: How to use it
B12: 1. Paste new bank lines into Bank columns A to D, under the last row.
B13: 2. Enter invoices and bills in Ledger columns A to F. One row per document, never one row per payment.
B14: 3. Read Exceptions. If everything there is zero, the period reconciles.
B15: 4. AR Aging tells you who to chase. AP Payment Run is the week's payments - filter column A for Yes.
B16: Every other column is a formula and rebuilds itself. Do not overwrite them.
B18: Design decisions, and why
B20: Whole-column references. A bounded range like E2:E150 breaks silently when somebody pastes in a longer month - it keeps calculating and reports a wrong number for that month. Whole columns cost a little speed and remove a whole class of silent error.
... B33: The data is synthetic and the business is invented. This is a demonstration of method, not client work, and it is not presented as anything else.

Sheet Bank
A1: Bank statement - paste new lines under the last row
A2: Columns A-D are the only ones you type. E to H are formulas and rebuild themselves; do not overwrite them. | F2: Opening balance | G2: 0 | H2: <- type these two from the statement
F3: Closing balance per statement | G3: 0
A4: Date | B4: Bank description | C4: Money in | D4: Money out | E4: Net | F4: Match key | G4: In ledger | H4: Status
E5: =N(C5)-N(D5) | F5: =IF(E5=0,"",TEXT(ABS(E5),"0.00")&"|"&IF(E5>0,"AR","AP")) | G5: =IF(F5="","",COUNTIF(Ledger!$H:$H,F5)) | H5: =IF(F5="","",IF(COUNTIF($F:$F,F5)>1,"REVIEW - same amount appears twice",IF(G5=0,"UNMATCHED - no ledger entry",IF(G5>1,"REVIEW - matches several ledger entries","Matched"))))
E6: =N(C6)-N(D6) | F6: =IF(E6=0,"",TEXT(ABS(E6),"0.00")&"|"&IF(E6>0,"AR","AP")) | G6: =IF(F6="","",COUNTIF(Ledger!$H:$H,F6)) | H6: =IF(F6="","",IF(COUNTIF($F:$F,F6)>1,"REVIEW - same amount appears twice",IF(G6=0,"UNMATCHED - no ledger entry",IF(G6>1,"REVIEW - matches several ledger entries","Matched"))))
E7: =N(C7)-N(D7) | F7: =IF(E7=0,"",TEXT(ABS(E7),"0.00")&"|"&IF(E7>0,"AR","AP")) | G7: =IF(F7="","",COUNTIF(Ledger!$H:$H,F7)) | H7: =IF(F7="","",IF(COUNTIF($F:$F,F7)>1,"REVIEW - same amount appears twice",IF(G7=0,"UNMATCHED - no ledger entry",IF(G7>1,"REVIEW - matches several ledger entries","Matched"))))
E8: =N(C8)-N(D8) | F8: =IF(E8=0,"",TEXT(ABS(E8),"0.00")&"|"&IF(E8>0,"AR","AP")) | G8: =IF(F8="","",COUNTIF(Ledger!$H:$H,F8)) | H8: =IF(F8="","",IF(COUNTIF($F:$F,F8)>1,"REVIEW - same amount appears twice",IF(G8=0,"UNMATCHED - no ledger entry",IF(G8>1,"REVIEW - matches several ledger entries","Matched"))))
E9: =N(C9)-N(D9) | F9: =IF(E9=0,"",TEXT(ABS(E9),"0.00")&"|"&IF(E9>0,"AR","AP")) | G9: =IF(F9="","",COUNTIF(Ledger!$H:$H,F9)) | H9: =IF(F9="","",IF(COUNTIF($F:$F,F9)>1,"REVIEW - same amount appears twice",IF(G9=0,"UNMATCHED - no ledger entry",IF(G9>1,"REVIEW - matches several ledger entries","Matched"))))
E10: =N(C10)-N(D10) | F10: =IF(E10=0,"",TEXT(ABS(E10),"0.00")&"|"&IF(E10>0,"AR","AP")) | G10: =IF(F10="","",COUNTIF(Ledger!$H:$H,F10)) | H10: =IF(F10="","",IF(COUNTIF($F:$F,F10)>1,"REVIEW - same amount appears twice",IF(G10=0,"UNMATCHED - no ledger entry",IF(G10>1,"REVIEW - matches several ledger entries","Matched"))))
E11: =N(C11)-N(D11) | F11: =IF(E11=0,"",TEXT(ABS(E11),"0.00")&"|"&IF(E11>0,"AR","AP")) | G11: =IF(F11="","",COUNTIF(Ledger!$H:$H,F11)) | H11: =IF(F11="","",IF(COUNTIF($F:$F,F11)>1,"REVIEW - same amount appears twice",IF(G11=0,"UNMATCHED - no ledger entry",IF(G11>1,"REVIEW - matches several ledger entries","Matched"))))
E12: =N(C12)-N(D12) | F12: =IF(E12=0,"",TEXT(ABS(E12),"0.00")&"|"&IF(E12>0,"AR","AP")) | G12: =IF(F12="","",COUNTIF(Ledger!$H:$H,F12)) | H12: =IF(F12="","",IF(COUNTIF($F:$F,F12)>1,"REVIEW - same amount appears twice",IF(G12=0,"UNMATCHED - no ledger entry",IF(G12>1,"REVIEW - matches several ledger entries","Matched"))))
E13: =N(C13)-N(D13) | F13: =IF(E13=0,"",TEXT(ABS(E13),"0.00")&"|"&IF(E13>0,"AR","AP")) | G13: =IF(F13="","",COUNTIF(Ledger!$H:$H,F13)) | H13: =IF(F13="","",IF(COUNTIF($F:$F,F13)>1,"REVIEW - same amount appears twice",IF(G13=0,"UNMATCHED - no ledger entry",IF(G13>1,"REVIEW - matches several ledger entries","Matched"))))
E14: =N(C14)-N(D14) | F14: =IF(E14=0,"",TEXT(ABS(E14),"0.00")&"|"&IF(E14>0,"AR","AP")) | G14: =IF(F14="","",COUNTIF(Ledger!$H:$H,F14)) | H14: =IF(F14="","",IF(COUNTIF($F:$F,F14)>1,"REVIEW - same amount appears twice",IF(G14=0,"UNMATCHED - no ledger entry",IF(G14>1,"REVIEW - matches several ledger entries","Matched"))))
E15: =N(C15)-N(D15) | F15: =IF(E15=0,"",TEXT(ABS(E15),"0.00")&"|"&IF(E15>0,"AR","AP")) | G15: =IF(F15="","",COUNTIF(Ledger!$H:$H,F15)) | H15: =IF(F15="","",IF(COUNTIF($F:$F,F15)>1,"REVIEW - same amount appears twice",IF(G15=0,"UNMATCHED - no ledger entry",IF(G15>1,"REVIEW - matches several ledger entries","Matched"))))
E16: =N(C16)-N(D16) | F16: =IF(E16=0,"",TEXT(ABS(E16),"0.00")&"|"&IF(E16>0,"AR","AP")) | G16: =IF(F16="","",COUNTIF(Ledger!$H:$H,F16)) | H16: =IF(F16="","",IF(COUNTIF($F:$F,F16)>1,"REVIEW - same amount appears twice",IF(G16=0,"UNMATCHED - no ledger entry",IF(G16>1,"REVIEW - matches several ledger entries","Matched"))))
... E604: =N(C604)-N(D604) | F604: =IF(E604=0,"",TEXT(ABS(E604),"0.00")&"|"&IF(E604>0,"AR","AP")) | G604: =IF(F604="","",COUNTIF(Ledger!$H:$H,F604)) | H604: =IF(F604="","",IF(COUNTIF($F:$F,F604)>1,"REVIEW - same amount appears twice",IF(G604=0,"UNMATCHED - no ledger entry",IF(G604>1,"REVIEW - matches several ledger entries","Matched"))))

Sheet Ledger
A1: Ledger - invoices you raised and bills you received
A2: Columns A-F are typed. G to J are formulas. One row per document, never one row per payment.
A4: Date | B4: Type | C4: Party | D4: Reference | E4: Amount | F4: Due date | G4: Days overdue | H4: Match key | I4: Settled | J4: Aging bucket
G5: =IF(I5="Settled","",MAX(0,TODAY()-F5)) | H5: =IF(E5="","",TEXT(E5,"0.00")&"|"&IF(B5="Invoice","AR","AP")) | I5: =IF(H5="","",IF(COUNTIF(Bank!$F:$F,H5)>0,"Settled","Open")) | J5: =IF(I5<>"Open","",IF(G5<=0,"Current",IF(G5<=30,"1-30",IF(G5<=60,"31-60",IF(G5<=90,"61-90","90+")))))
G6: =IF(I6="Settled","",MAX(0,TODAY()-F6)) | H6: =IF(E6="","",TEXT(E6,"0.00")&"|"&IF(B6="Invoice","AR","AP")) | I6: =IF(H6="","",IF(COUNTIF(Bank!$F:$F,H6)>0,"Settled","Open")) | J6: =IF(I6<>"Open","",IF(G6<=0,"Current",IF(G6<=30,"1-30",IF(G6<=60,"31-60",IF(G6<=90,"61-90","90+")))))
G7: =IF(I7="Settled","",MAX(0,TODAY()-F7)) | H7: =IF(E7="","",TEXT(E7,"0.00")&"|"&IF(B7="Invoice","AR","AP")) | I7: =IF(H7="","",IF(COUNTIF(Bank!$F:$F,H7)>0,"Settled","Open")) | J7: =IF(I7<>"Open","",IF(G7<=0,"Current",IF(G7<=30,"1-30",IF(G7<=60,"31-60",IF(G7<=90,"61-90","90+")))))
G8: =IF(I8="Settled","",MAX(0,TODAY()-F8)) | H8: =IF(E8="","",TEXT(E8,"0.00")&"|"&IF(B8="Invoice","AR","AP")) | I8: =IF(H8="","",IF(COUNTIF(Bank!$F:$F,H8)>0,"Settled","Open")) | J8: =IF(I8<>"Open","",IF(G8<=0,"Current",IF(G8<=30,"1-30",IF(G8<=60,"31-60",IF(G8<=90,"61-90","90+")))))
G9: =IF(I9="Settled","",MAX(0,TODAY()-F9)) | H9: =IF(E9="","",TEXT(E9,"0.00")&"|"&IF(B9="Invoice","AR","AP")) | I9: =IF(H9="","",IF(COUNTIF(Bank!$F:$F,H9)>0,"Settled","Open")) | J9: =IF(I9<>"Open","",IF(G9<=0,"Current",IF(G9<=30,"1-30",IF(G9<=60,"31-60",IF(G9<=90,"61-90","90+")))))
G10: =IF(I10="Settled","",MAX(0,TODAY()-F10)) | H10: =IF(E10="","",TEXT(E10,"0.00")&"|"&IF(B10="Invoice","AR","AP")) | I10: =IF(H10="","",IF(COUNTIF(Bank!$F:$F,H10)>0,"Settled","Open")) | J10: =IF(I10<>"Open","",IF(G10<=0,"Current",IF(G10<=30,"1-30",IF(G10<=60,"31-60",IF(G10<=90,"61-90","90+")))))
G11: =IF(I11="Settled","",MAX(0,TODAY()-F11)) | H11: =IF(E11="","",TEXT(E11,"0.00")&"|"&IF(B11="Invoice","AR","AP")) | I11: =IF(H11="","",IF(COUNTIF(Bank!$F:$F,H11)>0,"Settled","Open")) | J11: =IF(I11<>"Open","",IF(G11<=0,"Current",IF(G11<=30,"1-30",IF(G11<=60,"31-60",IF(G11<=90,"61-90","90+")))))
G12: =IF(I12="Settled","",MAX(0,TODAY()-F12)) | H12: =IF(E12="","",TEXT(E12,"0.00")&"|"&IF(B12="Invoice","AR","AP")) | I12: =IF(H12="","",IF(COUNTIF(Bank!$F:$F,H12)>0,"Settled","Open")) | J12: =IF(I12<>"Open","",IF(G12<=0,"Current",IF(G12<=30,"1-30",IF(G12<=60,"31-60",IF(G12<=90,"61-90","90+")))))
G13: =IF(I13="Settled","",MAX(0,TODAY()-F13)) | H13: =IF(E13="","",TEXT(E13,"0.00")&"|"&IF(B13="Invoice","AR","AP")) | I13: =IF(H13="","",IF(COUNTIF(Bank!$F:$F,H13)>0,"Settled","Open")) | J13: =IF(I13<>"Open","",IF(G13<=0,"Current",IF(G13<=30,"1-30",IF(G13<=60,"31-60",IF(G13<=90,"61-90","90+")))))
G14: =IF(I14="Settled","",MAX(0,TODAY()-F14)) | H14: =IF(E14="","",TEXT(E14,"0.00")&"|"&IF(B14="Invoice","AR","AP")) | I14: =IF(H14="","",IF(COUNTIF(Bank!$F:$F,H14)>0,"Settled","Open")) | J14: =IF(I14<>"Open","",IF(G14<=0,"Current",IF(G14<=30,"1-30",IF(G14<=60,"31-60",IF(G14<=90,"61-90","90+")))))
G15: =IF(I15="Settled","",MAX(0,TODAY()-F15)) | H15: =IF(E15="","",TEXT(E15,"0.00")&"|"&IF(B15="Invoice","AR","AP")) | I15: =IF(H15="","",IF(COUNTIF(Bank!$F:$F,H15)>0,"Settled","Open")) | J15: =IF(I15<>"Open","",IF(G15<=0,"Current",IF(G15<=30,"1-30",IF(G15<=60,"31-60",IF(G15<=90,"61-90","90+")))))
G16: =IF(I16="Settled","",MAX(0,TODAY()-F16)) | H16: =IF(E16="","",TEXT(E16,"0.00")&"|"&IF(B16="Invoice","AR","AP")) | I16: =IF(H16="","",IF(COUNTIF(Bank!$F:$F,H16)>0,"Settled","Open")) | J16: =IF(I16<>"Open","",IF(G16<=0,"Current",IF(G16<=30,"1-30",IF(G16<=60,"31-60",IF(G16<=90,"61-90","90+")))))
... G604: =IF(I604="Settled","",MAX(0,TODAY()-F604)) | H604: =IF(E604="","",TEXT(E604,"0.00")&"|"&IF(B604="Invoice","AR","AP")) | I604: =IF(H604="","",IF(COUNTIF(Bank!$F:$F,H604)>0,"Settled","Open")) | J604: =IF(I604<>"Open","",IF(G604<=0,"Current",IF(G604<=30,"1-30",IF(G604<=60,"31-60",IF(G604<=90,"61-90","90+")))))

Sheet Exceptions
A1: Exceptions - the only sheet that needs your attention
A2: Checked from both directions. A bill entered twice and paid once is invisible if you only check the bank side.
A4: Check | B4: Count | C4: What it means and what to do
A5: Bank lines with no matching ledger entry | B5: =COUNTIF(Bank!$H:$H,"UNMATCHED*") | C5: Money moved that the books do not explain. Usually a fee, a transfer between own accounts, or a bill nobody entered.
A6: Bank lines needing review for ambiguity | B6: =COUNTIF(Bank!$H:$H,"REVIEW*") | C6: Either the same amount appears twice on the statement - a possible double payment - or it matches several ledger entries. Matching on amount cannot tell these apart, so confirm by reference before ticking any of them off.
A7: Ledger entries still open past their due date | B7: =COUNTIFS(Ledger!$I:$I,"Open",Ledger!$G:$G,">0") | C7: Overdue both ways: invoices to chase and bills you are late paying.
A8: Invoices unpaid more than 60 days | B8: =COUNTIFS(Ledger!$I:$I,"Open",Ledger!$B:$B,"Invoice",Ledger!$G:$G,">60") | C8: The number that turns into a write-off if nobody looks at it.
A9: Duplicate references in the ledger | B9: =SUMPRODUCT((Ledger!$D$5:$D$500<>"")*(COUNTIF(Ledger!$D$5:$D$500,Ledger!$D$5:$D$500)>1))/2 | C9: The same invoice or bill entered twice. Halved because each duplicate pair is counted from both ends.

Sheet AR Aging
A1: Receivables aging - who to chase, in what order
A2: Buckets recalculate from TODAY(). Nothing here is typed.
A4: Customer | B4: Current | C4: 1-30 days | D4: 31-60 days | E4: 61-90 days | F4: 90+ days | G4: Total open
A5: Harding Construction | B5: =SUMIFS(Ledger!$E:$E,Ledger!$C:$C,$A5,Ledger!$B:$B,"Invoice",Ledger!$I:$I,"Open",Ledger!$J:$J,"Current") | C5: =SUMIFS(Ledger!$E:$E,Ledger!$C:$C,$A5,Ledger!$B:$B,"Invoice",Ledger!$I:$I,"Open",Ledger!$J:$J,"1-30") | D5: =SUMIFS(Ledger!$E:$E,Ledger!$C:$C,$A5,Ledger!$B:$B,"Invoice",Ledger!$I:$I,"Open",Ledger!$J:$J,"31-60") | E5: =SUMIFS(Ledger!$E:$E,Ledger!$C:$C,$A5,Ledger!$B:$B,"Invoice",Ledger!$I:$I,"Open",Ledger!$J:$J,"61-90") | F5: =SUMIFS(Ledger!$E:$E,Ledger!$C:$C,$A5,Ledger!$B:$B,"Invoice",Ledger!$I:$I,"Open",Ledger!$J:$J,"90+") | G5: =SUM(B5:F5)
A6: Bayline Interiors | B6: =SUMIFS(Ledger!$E:$E,Ledger!$C:$C,$A6,Ledger!$B:$B,"Invoice",Ledger!$I:$I,"Open",Ledger!$J:$J,"Current") | C6: =SUMIFS(Ledger!$E:$E,Ledger!$C:$C,$A6,Ledger!$B:$B,"Invoice",Ledger!$I:$I,"Open",Ledger!$J:$J,"1-30") | D6: =SUMIFS(Ledger!$E:$E,Ledger!$C:$C,$A6,Ledger!$B:$B,"Invoice",Ledger!$I:$I,"Open",Ledger!$J:$J,"31-60") | E6: =SUMIFS(Ledger!$E:$E,Ledger!$C:$C,$A6,Ledger!$B:$B,"Invoice",Ledger!$I:$I,"Open",Ledger!$J:$J,"61-90") | F6: =SUMIFS(Ledger!$E:$E,Ledger!$C:$C,$A6,Ledger!$B:$B,"Invoice",Ledger!$I:$I,"Open",Ledger!$J:$J,"90+") | G6: =SUM(B6:F6)
A7: Crestwood Builders | B7: =SUMIFS(Ledger!$E:$E,Ledger!$C:$C,$A7,Ledger!$B:$B,"Invoice",Ledger!$I:$I,"Open",Ledger!$J:$J,"Current") | C7: =SUMIFS(Ledger!$E:$E,Ledger!$C:$C,$A7,Ledger!$B:$B,"Invoice",Ledger!$I:$I,"Open",Ledger!$J:$J,"1-30") | D7: =SUMIFS(Ledger!$E:$E,Ledger!$C:$C,$A7,Ledger!$B:$B,"Invoice",Ledger!$I:$I,"Open",Ledger!$J:$J,"31-60") | E7: =SUMIFS(Ledger!$E:$E,Ledger!$C:$C,$A7,Ledger!$B:$B,"Invoice",Ledger!$I:$I,"Open",Ledger!$J:$J,"61-90") | F7: =SUMIFS(Ledger!$E:$E,Ledger!$C:$C,$A7,Ledger!$B:$B,"Invoice",Ledger!$I:$I,"Open",Ledger!$J:$J,"90+") | G7: =SUM(B7:F7)
A8: Dockside Marine | B8: =SUMIFS(Ledger!$E:$E,Ledger!$C:$C,$A8,Ledger!$B:$B,"Invoice",Ledger!$I:$I,"Open",Ledger!$J:$J,"Current") | C8: =SUMIFS(Ledger!$E:$E,Ledger!$C:$C,$A8,Ledger!$B:$B,"Invoice",Ledger!$I:$I,"Open",Ledger!$J:$J,"1-30") | D8: =SUMIFS(Ledger!$E:$E,Ledger!$C:$C,$A8,Ledger!$B:$B,"Invoice",Ledger!$I:$I,"Open",Ledger!$J:$J,"31-60") | E8: =SUMIFS(Ledger!$E:$E,Ledger!$C:$C,$A8,Ledger!$B:$B,"Invoice",Ledger!$I:$I,"Open",Ledger!$J:$J,"61-90") | F8: =SUMIFS(Ledger!$E:$E,Ledger!$C:$C,$A8,Ledger!$B:$B,"Invoice",Ledger!$I:$I,"Open",Ledger!$J:$J,"90+") | G8: =SUM(B8:F8)
A9: Vale & Sons Painting | B9: =SUMIFS(Ledger!$E:$E,Ledger!$C:$C,$A9,Ledger!$B:$B,"Invoice",Ledger!$I:$I,"Open",Ledger!$J:$J,"Current") | C9: =SUMIFS(Ledger!$E:$E,Ledger!$C:$C,$A9,Ledger!$B:$B,"Invoice",Ledger!$I:$I,"Open",Ledger!$J:$J,"1-30") | D9: =SUMIFS(Ledger!$E:$E,Ledger!$C:$C,$A9,Ledger!$B:$B,"Invoice",Ledger!$I:$I,"Open",Ledger!$J:$J,"31-60") | E9: =SUMIFS(Ledger!$E:$E,Ledger!$C:$C,$A9,Ledger!$B:$B,"Invoice",Ledger!$I:$I,"Open",Ledger!$J:$J,"61-90") | F9: =SUMIFS(Ledger!$E:$E,Ledger!$C:$C,$A9,Ledger!$B:$B,"Invoice",Ledger!$I:$I,"Open",Ledger!$J:$J,"90+") | G9: =SUM(B9:F9)
A10: Northgate Property Co | B10: =SUMIFS(Ledger!$E:$E,Ledger!$C:$C,$A10,Ledger!$B:$B,"Invoice",Ledger!$I:$I,"Open",Ledger!$J:$J,"Current") | C10: =SUMIFS(Ledger!$E:$E,Ledger!$C:$C,$A10,Ledger!$B:$B,"Invoice",Ledger!$I:$I,"Open",Ledger!$J:$J,"1-30") | D10: =SUMIFS(Ledger!$E:$E,Ledger!$C:$C,$A10,Ledger!$B:$B,"Invoice",Ledger!$I:$I,"Open",Ledger!$J:$J,"31-60") | E10: =SUMIFS(Ledger!$E:$E,Ledger!$C:$C,$A10,Ledger!$B:$B,"Invoice",Ledger!$I:$I,"Open",Ledger!$J:$J,"61-90") | F10: =SUMIFS(Ledger!$E:$E,Ledger!$C:$C,$A10,Ledger!$B:$B,"Invoice",Ledger!$I:$I,"Open",Ledger!$J:$J,"90+") | G10: =SUM(B10:F10)
A11: Ellerslie Fitout | B11: =SUMIFS(Ledger!$E:$E,Ledger!$C:$C,$A11,Ledger!$B:$B,"Invoice",Ledger!$I:$I,"Open",Ledger!$J:$J,"Current") | C11: =SUMIFS(Ledger!$E:$E,Ledger!$C:$C,$A11,Ledger!$B:$B,"Invoice",Ledger!$I:$I,"Open",Ledger!$J:$J,"1-30") | D11: =SUMIFS(Ledger!$E:$E,Ledger!$C:$C,$A11,Ledger!$B:$B,"Invoice",Ledger!$I:$I,"Open",Ledger!$J:$J,"31-60") | E11: =SUMIFS(Ledger!$E:$E,Ledger!$C:$C,$A11,Ledger!$B:$B,"Invoice",Ledger!$I:$I,"Open",Ledger!$J:$J,"61-90") | F11: =SUMIFS(Ledger!$E:$E,Ledger!$C:$C,$A11,Ledger!$B:$B,"Invoice",Ledger!$I:$I,"Open",Ledger!$J:$J,"90+") | G11: =SUM(B11:F11)
A12: Quay Street Developments | B12: =SUMIFS(Ledger!$E:$E,Ledger!$C:$C,$A12,Ledger!$B:$B,"Invoice",Ledger!$I:$I,"Open",Ledger!$J:$J,"Current") | C12: =SUMIFS(Ledger!$E:$E,Ledger!$C:$C,$A12,Ledger!$B:$B,"Invoice",Ledger!$I:$I,"Open",Ledger!$J:$J,"1-30") | D12: =SUMIFS(Ledger!$E:$E,Ledger!$C:$C,$A12,Ledger!$B:$B,"Invoice",Ledger!$I:$I,"Open",Ledger!$J:$J,"31-60") | E12: =SUMIFS(Ledger!$E:$E,Ledger!$C:$C,$A12,Ledger!$B:$B,"Invoice",Ledger!$I:$I,"Open",Ledger!$J:$J,"61-90") | F12: =SUMIFS(Ledger!$E:$E,Ledger!$C:$C,$A12,Ledger!$B:$B,"Invoice",Ledger!$I:$I,"Open",Ledger!$J:$J,"90+") | G12: =SUM(B12:F12)
A13: Total | B13: =SUM(B5:B12) | C13: =SUM(C5:C12) | D13: =SUM(D5:D12) | E13: =SUM(E5:E12) | F13: =SUM(F5:F12) | G13: =SUM(G5:G12)

Sheet AP Payment Run
A1: Supplier payment run - what is due in the next 7 days
A2: Filter column A for Yes. Sorted by the ledger, so a bill cannot appear here without existing in the books.
A4: Pay this run? | B4: Supplier | C4: Reference | D4: Amount | E4: Due date | F4: Days overdue
A5: =IF(Ledger!I5<>"Open","",IF(Ledger!F5<=TODAY()+7,"Yes","-")) | B5: =Ledger!C5 | C5: =Ledger!D5 | D5: =Ledger!E5 | E5: =Ledger!F5 | F5: =Ledger!G5
A6: =IF(Ledger!I6<>"Open","",IF(Ledger!F6<=TODAY()+7,"Yes","-")) | B6: =Ledger!C6 | C6: =Ledger!D6 | D6: =Ledger!E6 | E6: =Ledger!F6 | F6: =Ledger!G6
A7: =IF(Ledger!I7<>"Open","",IF(Ledger!F7<=TODAY()+7,"Yes","-")) | B7: =Ledger!C7 | C7: =Ledger!D7 | D7: =Ledger!E7 | E7: =Ledger!F7 | F7: =Ledger!G7
A8: =IF(Ledger!I8<>"Open","",IF(Ledger!F8<=TODAY()+7,"Yes","-")) | B8: =Ledger!C8 | C8: =Ledger!D8 | D8: =Ledger!E8 | E8: =Ledger!F8 | F8: =Ledger!G8
A9: =IF(Ledger!I9<>"Open","",IF(Ledger!F9<=TODAY()+7,"Yes","-")) | B9: =Ledger!C9 | C9: =Ledger!D9 | D9: =Ledger!E9 | E9: =Ledger!F9 | F9: =Ledger!G9
A10: =IF(Ledger!I10<>"Open","",IF(Ledger!F10<=TODAY()+7,"Yes","-")) | B10: =Ledger!C10 | C10: =Ledger!D10 | D10: =Ledger!E10 | E10: =Ledger!F10 | F10: =Ledger!G10
A11: =IF(Ledger!I11<>"Open","",IF(Ledger!F11<=TODAY()+7,"Yes","-")) | B11: =Ledger!C11 | C11: =Ledger!D11 | D11: =Ledger!E11 | E11: =Ledger!F11 | F11: =Ledger!G11
A12: =IF(Ledger!I12<>"Open","",IF(Ledger!F12<=TODAY()+7,"Yes","-")) | B12: =Ledger!C12 | C12: =Ledger!D12 | D12: =Ledger!E12 | E12: =Ledger!F12 | F12: =Ledger!G12
A13: =IF(Ledger!I13<>"Open","",IF(Ledger!F13<=TODAY()+7,"Yes","-")) | B13: =Ledger!C13 | C13: =Ledger!D13 | D13: =Ledger!E13 | E13: =Ledger!F13 | F13: =Ledger!G13
A14: =IF(Ledger!I14<>"Open","",IF(Ledger!F14<=TODAY()+7,"Yes","-")) | B14: =Ledger!C14 | C14: =Ledger!D14 | D14: =Ledger!E14 | E14: =Ledger!F14 | F14: =Ledger!G14
A15: =IF(Ledger!I15<>"Open","",IF(Ledger!F15<=TODAY()+7,"Yes","-")) | B15: =Ledger!C15 | C15: =Ledger!D15 | D15: =Ledger!E15 | E15: =Ledger!F15 | F15: =Ledger!G15
A16: =IF(Ledger!I16<>"Open","",IF(Ledger!F16<=TODAY()+7,"Yes","-")) | B16: =Ledger!C16 | C16: =Ledger!D16 | D16: =Ledger!E16 | E16: =Ledger!F16 | F16: =Ledger!G16
... A604: =IF(Ledger!I604<>"Open","",IF(Ledger!F604<=TODAY()+7,"Yes","-")) | B604: =Ledger!C604 | C604: =Ledger!D604 | D604: =Ledger!E604 | E604: =Ledger!F604 | F604: =Ledger!G604

Sheet Dashboard
B2: Bank Reconciliation and AP/AR
B3: Your business - paste your statement into Bank, your invoices and bills into Ledger.
B5: Unreconciled bank lines | E5: Lines needing review
B6: =COUNTIF(Bank!$H:$H,"UNMATCHED*") | E6: =COUNTIF(Bank!$H:$H,"REVIEW*")
B9: Receivables outstanding | E9: Payables outstanding
B10: =SUMIFS(Ledger!$E:$E,Ledger!$B:$B,"Invoice",Ledger!$I:$I,"Open") | E10: =SUMIFS(Ledger!$E:$E,Ledger!$B:$B,"Bill",Ledger!$I:$I,"Open")
B13: Overdue receivables | E13: Due to suppliers within 7 days
B14: =SUMIFS(Ledger!$E:$E,Ledger!$B:$B,"Invoice",Ledger!$I:$I,"Open",Ledger!$G:$G,">0") | E14: =SUMPRODUCT((Ledger!$B$5:$B$500="Bill")*(Ledger!$I$5:$I$500="Open")*(Ledger!$F$5:$F$500<=TODAY()+7)*(Ledger!$F$5:$F$500<>"")*Ledger!$E$5:$E$500)
B17: Reconciled this period
B18: =TEXT(COUNTIF(Bank!$H:$H,"Matched")/MAX(1,COUNTIF(Bank!$H:$H,"Matched")+COUNTIF(Bank!$H:$H,"UNMATCHED*")+COUNTIF(Bank!$H:$H,"REVIEW*")),"0%")&" of bank lines matched to a ledger entry"
B20: Does the cash agree?
B21: Closing balance per the books | C21: =Bank!$G$2+SUM(Bank!$E:$E)
B22: Closing balance per the statement | C22: =Bank!$G$3
B23: Variance | C23: =ROUND(C21-C22,2) | E23: =IF(ROUND(C23,2)=0,"Reconciled - the cash agrees to the penny","NOT RECONCILED - find the difference before doing anything else")
B26: How to read this
B27: - Unreconciled bank lines - money moved that the books do not explain. Work these first; everything else is arithmetic.
B28: - Lines needing review - the same amount twice on the statement, or one that matches several ledger entries. The sheet will not guess which is which, and neither should you.
B29: - Overdue receivables is the number a business owner actually wants. Receivables outstanding includes invoices that are not late yet.
B30: - Aging buckets and the payment run both recalculate from TODAY(), so this workbook is still correct next month without being edited.
B31: - A zero variance does NOT mean the books are right. The cash can agree to the penny while transactions above still have no explanation - agreeing and being correct are different questions, and this sheet asks both.
